{
  "sleep": [
    "Dein Kopf wird nicht leiser?",
    "Sanfter Regen zum Loslassen.",
    "Rauschen, aber lebendig.",
    "Schließ die Augen. Du bist woanders.",
    "Bau dir deine Hütte im Regen."
  ],
  "focus": [
    "Wenn Stille zu laut wird.",
    "Ein Klangteppich, der dich drin hält.",
    "Arbeiten, ohne abzudriften.",
    "Bau dir deine Fokusblase.",
    "Weniger Lärm. Mehr Präsenz."
  ],
  "spatial": [
    "Platziere den Regen hinter dir.",
    "Schieb das Gewitter in die Ferne.",
    "Eine Klanglandschaft um dich herum.",
    "Natur, um dich herum platziert.",
    "Klang, der nicht aus einem Bildschirm kommt."
  ],
  "antiSubscription": [
    "Nicht noch ein Abo.",
    "Eine ruhige App. Einmal kaufen.",
    "Premium ohne monatliche Falle.",
    "Endlich eine Entspannungs-App ohne Abo."
  ],
  "founder": [
    "Ich habe diese App gebaut, um billige Audio-Loops zu ersetzen.",
    "Eine Indie-App, gemacht für langes Hören.",
    "Ich wollte eine Atmosphäre, die wirklich atmet."
  ]
}
